addict/__init__.py
addict/addict.py
addict-2.3.0.dist-info/LICENSE
addict-2.3.0.dist-info/METADATA
addict-2.3.0.dist-info/WHEEL
addict-2.3.0.dist-info/top_level.txt
addict-2.3.0.dist-info/RECORD
