Metadata-Version: 2.1
Name: addict
Version: 2.3.0
Summary: Addict is a dictionary whose items can be set using both attribute and item syntax.
Home-page: https://github.com/mewwts/addict
Author: Mats Julian Olsen
Author-email: mats@plysjbyen.net
License: UNKNOWN
Platform: UNKNOWN
Classifier: Programming Language :: Python
Classifier: Programming Language :: Python :: 2.7
Classifier: Programming Language :: Python :: 3.6
Classifier: Programming Language :: Python :: 3.7
Classifier: Programming Language :: Python :: 3.8
Classifier: Programming Language :: Python :: 3.9
Classifier: License :: OSI Approved :: MIT License
Classifier: Operating System :: OS Independent
Classifier: Intended Audience :: Developers
Classifier: Topic :: Software Development :: Libraries :: Python Modules
